teleporter/__init__.py
teleporter/__version__.py
teleporter/teleporter.py
teleporter/android/__init__.py
teleporter/android/android.py
teleporter/android/auth.py
teleporter/android/datacenter.py
teleporter/android/headers.py
teleporter/android/native_byte_buffer.py
teleporter/android/salt.py
teleporter/android_x/__init__.py
teleporter/android_x/aes_ctr_encryption_event.py
teleporter/android_x/android_x.py
teleporter/android_x/binlog_event.py
teleporter/android_x/handler_type.py
teleporter/android_x/tl_parser.py
teleporter/core/__init__.py
teleporter/core/get_session_file_path.py
teleporter/core/int.py
teleporter/core/ip.py
teleporter/core/tgcrypto.py
teleporter/desktop/__init__.py
teleporter/desktop/aes_local.py
teleporter/desktop/create_local_key.py
teleporter/desktop/decrypt_local.py
teleporter/desktop/desktop.py
teleporter/desktop/file.py
teleporter/desktop/file_write_descriptor.py
teleporter/desktop/generate_local_key.py
teleporter/desktop/map.py
teleporter/desktop/to_file_part.py
teleporter/pyrogram/__init__.py
teleporter/pyrogram/pyrogram.py
teleporter/telethon/__init__.py
teleporter/telethon/telethon.py
teleporter/web/__init__.py
teleporter/web/web.py
teleporter-6.1.0.dist-info/METADATA
teleporter-6.1.0.dist-info/WHEEL
teleporter-6.1.0.dist-info/top_level.txt
teleporter-6.1.0.dist-info/RECORD
