Metadata-Version: 2.1
Name: teleporter
Version: 6.1.0
Summary: tool with almost zero dependencies that allows you to switch Telegram session from/to Android, Android X, Desktop, Web, Telethon or Pyrogram client
Home-page: https://github.com/sozercanye/teleporter
Author: sozercanye
Requires-Python: >=3.9
